<?xml version="1.0" encoding="utf-8" ?>
<hibernate-mapping xmlns="urn:nhibernate-mapping-2.2">

<class name="SPS.Entity.Tables.SPSClientEntity,SPS.Entity" table="SPSClient" lazy="true"  >

<id name="Id" column="ID" type="int" unsaved-value="0" >
   <generator class="native">

</generator>

</id>


		<property column="Name" type="string" name="Name"   not-null="true"  length="400" />	
		<property column="Description" type="string" name="Description"   not-null="true"  length="4000" />	
		<property column="UserID" type="int" name="UserID"   not-null="true"  />	
		<property column="IsDefaultClient" type="Boolean" name="IsDefaultClient"   />	
		<property column="SyncData" type="Boolean" name="SyncData"   not-null="true"  />	
		<property column="SycnRetryTimes" type="int" name="SycnRetryTimes"   />	
		<property column="SyncType" type="string" name="SyncType"   length="100" />	
		<property column="SycnNotInterceptCount" type="int" name="SycnNotInterceptCount"   />	
		<property column="SycnDataUrl" type="string" name="SycnDataUrl"   length="400" />	
		<property column="SycnOkMessage" type="string" name="SycnOkMessage"   length="100" />	
		<property column="SycnFailedMessage" type="string" name="SycnFailedMessage"   length="100" />	
		<property column="Alias" type="string" name="Alias"   length="400" />	
		<property column="InterceptRate" type="Decimal" name="InterceptRate"   not-null="true"  />	
		<property column="DefaultPrice" type="Decimal" name="DefaultPrice"   not-null="true"  />	
		<property column="DefaultShowRecordDays" type="int" name="DefaultShowRecordDays"   not-null="true"  />	
		<property column="CreateBy" type="int" name="CreateBy"   />	
		<property column="CreateAt" type="DateTime" name="CreateAt"   />	
		<property column="LastModifyBy" type="int" name="LastModifyBy"   />	
		<property column="LastModifyAt" type="DateTime" name="LastModifyAt"   />	
		<property column="LastModifyComment" type="string" name="LastModifyComment"   length="600" />	




</class>
</hibernate-mapping>
